{
    "version": "0.5.2",
    "description": "Browser session CLI with Native Messaging relay",
    "homepage": "https://github.com/4fuu/open-browser-cli",
    "license": "MIT",
    "architecture": {
        "64bit": {
            "url": "https://github.com/4fuu/open-browser-cli/releases/download/0.5.2/browser-cli-x86_64-pc-windows-msvc.zip",
            "hash": "9154fb1521953e733a350877308b01515cc85058ec683849be779e9e663c1d7d"
        }
    },
    "bin": "browser-cli.exe",
    "checkver": {
        "github": "https://github.com/4fuu/open-browser-cli"
    },
    "autoupdate": {
        "architecture": {
            "64bit": {
                "url": "https://github.com/4fuu/open-browser-cli/releases/download/0.5.2/browser-cli-x86_64-pc-windows-msvc.zip"
            }
        }
    }
}
